demo/__init__.py
webscaff/__init__.py
webscaff/cli.py
webscaff/exceptions.py
webscaff/overrides.py
webscaff/utils.py
webscaff/commands/__init__.py
webscaff/commands/utils.py
webscaff/commands/run/__init__.py
webscaff/commands/run/certbot.py
webscaff/commands/run/dj.py
webscaff/commands/run/fs.py
webscaff/commands/run/git.py
webscaff/commands/run/log.py
webscaff/commands/run/pg.py
webscaff/commands/run/service.py
webscaff/commands/run/utils.py
webscaff/commands/run/uwsgi.py
webscaff/commands/run/venv.py
webscaff/commands/sys/__init__.py
webscaff/commands/sys/apt.py
webscaff/commands/sys/fs.py
webscaff/commands/sys/git.py
webscaff/commands/sys/pg.py
webscaff/commands/sys/usr.py
webscaff/commands/sys/utils.py
webscaff/commands/sys/venv.py
webscaff-1.0.0.dist-info/AUTHORS
webscaff-1.0.0.dist-info/LICENSE
webscaff-1.0.0.dist-info/METADATA
webscaff-1.0.0.dist-info/WHEEL
webscaff-1.0.0.dist-info/entry_points.txt
webscaff-1.0.0.dist-info/top_level.txt
webscaff-1.0.0.dist-info/RECORD
