Metadata-Version: 2.1
Name: webscaff
Version: 1.0.0
Summary: Remote scaffolding and orchestration for web applications
Home-page: https://github.com/idlesign/webscaff
Author: Igor `idle sign` Starikov
Author-email: idlesign@yandex.ru
License: BSD 3-Clause License
Platform: UNKNOWN
Classifier: Development Status :: 4 - Beta
Classifier: Operating System :: OS Independent
Classifier: Programming Language :: Python
Classifier: Programming Language :: Python :: 3
Classifier: Programming Language :: Python :: 3.6
Classifier: Programming Language :: Python :: 3.7
Classifier: Programming Language :: Python :: 3.8
Classifier: Programming Language :: Python :: 3.9
Classifier: Programming Language :: Python :: 3.10
Classifier: Programming Language :: Python :: 3.11
Classifier: License :: OSI Approved :: BSD License
Requires-Dist: fabric (>=2.7.1)
Requires-Dist: invoke (>=1.7.3)
Requires-Dist: paramiko (>=2.12.0)
Requires-Dist: patchwork (>=1.0.1)
